{"imageURL":"public/img/towerDefense_tilesheet.png","frames":[{"name":"000","rect":[0,0,64,64]},{"name":"001","rect":[64,0,64,64]},{"name":"002","rect":[128,0,64,64]},{"name":"003","rect":[192,0,64,64]},{"name":"004","rect":[256,0,64,64]},{"name":"005","rect":[320,0,64,64]},{"name":"006","rect":[384,0,64,64]},{"name":"007","rect":[448,0,64,64]},{"name":"008","rect":[512,0,64,64]},{"name":"009","rect":[576,0,64,64]},{"name":"010","rect":[0,64,64,64]},{"name":"011","rect":[64,64,64,64]},{"name":"012","rect":[128,64,64,64]},{"name":"013","rect":[192,64,64,64]},{"name":"014","rect":[256,64,64,64]},{"name":"015","rect":[320,64,64,64]},{"name":"016","rect":[384,64,64,64]},{"name":"017","rect":[448,64,64,64]},{"name":"018","rect":[512,64,64,64]},{"name":"019","rect":[576,64,64,64]},{"name":"020","rect":[0,128,64,64]},{"name":"021","rect":[64,128,64,64]},{"name":"022","rect":[128,128,64,64]},{"name":"023","rect":[192,128,64,64]},{"name":"024","rect":[256,128,64,64]},{"name":"025","rect":[320,128,64,64]},{"name":"026","rect":[384,128,64,64]},{"name":"027","rect":[448,128,64,64]},{"name":"028","rect":[512,128,64,64]},{"name":"029","rect":[576,128,64,64]},{"name":"030","rect":[0,192,64,64]},{"name":"031","rect":[64,192,64,64]},{"name":"032","rect":[128,192,64,64]},{"name":"033","rect":[192,192,64,64]},{"name":"034","rect":[256,192,64,64]},{"name":"035","rect":[320,192,64,64]},{"name":"036","rect":[384,192,64,64]},{"name":"037","rect":[448,192,64,64]},{"name":"038","rect":[512,192,64,64]},{"name":"039","rect":[576,192,64,64]},{"name":"040","rect":[0,256,64,64]},{"name":"041","rect":[64,256,64,64]},{"name":"042","rect":[128,256,64,64]},{"name":"043","rect":[192,256,64,64]},{"name":"044","rect":[256,256,64,64]},{"name":"045","rect":[320,256,64,64]},{"name":"046","rect":[384,256,64,64]},{"name":"047","rect":[448,256,64,64]},{"name":"048","rect":[512,256,64,64]},{"name":"049","rect":[576,256,64,64]},{"name":"050","rect":[0,320,64,64]},{"name":"051","rect":[64,320,64,64]},{"name":"052","rect":[128,320,64,64]},{"name":"053","rect":[192,320,64,64]},{"name":"054","rect":[256,320,64,64]},{"name":"055","rect":[320,320,64,64]},{"name":"056","rect":[384,320,64,64]},{"name":"057","rect":[448,320,64,64]},{"name":"058","rect":[512,320,64,64]},{"name":"059","rect":[576,320,64,64]},{"name":"060","rect":[0,384,64,64]},{"name":"061","rect":[64,384,64,64]},{"name":"062","rect":[128,384,64,64]},{"name":"063","rect":[192,384,64,64]},{"name":"064","rect":[256,384,64,64]},{"name":"065","rect":[320,384,64,64]},{"name":"066","rect":[384,384,64,64]},{"name":"067","rect":[448,384,64,64]},{"name":"068","rect":[512,384,64,64]},{"name":"069","rect":[576,384,64,64]},{"name":"070","rect":[0,448,64,64]},{"name":"071","rect":[64,448,64,64]},{"name":"072","rect":[128,448,64,64]},{"name":"073","rect":[192,448,64,64]},{"name":"074","rect":[256,448,64,64]},{"name":"075","rect":[320,448,64,64]},{"name":"076","rect":[384,448,64,64]},{"name":"077","rect":[448,448,64,64]},{"name":"078","rect":[512,448,64,64]},{"name":"079","rect":[576,448,64,64]},{"name":"080","rect":[0,512,64,64]},{"name":"081","rect":[64,512,64,64]},{"name":"082","rect":[128,512,64,64]},{"name":"083","rect":[192,512,64,64]},{"name":"084","rect":[256,512,64,64]},{"name":"085","rect":[320,512,64,64]},{"name":"086","rect":[384,512,64,64]},{"name":"087","rect":[448,512,64,64]},{"name":"088","rect":[512,512,64,64]},{"name":"089","rect":[576,512,64,64]},{"name":"090","rect":[0,576,64,64]},{"name":"091","rect":[64,576,64,64]},{"name":"092","rect":[128,576,64,64]},{"name":"093","rect":[192,576,64,64]},{"name":"094","rect":[256,576,64,64]},{"name":"095","rect":[320,576,64,64]},{"name":"096","rect":[384,576,64,64]},{"name":"097","rect":[448,576,64,64]},{"name":"098","rect":[512,576,64,64]},{"name":"099","rect":[576,576,64,64]},{"name":"100","rect":[0,640,64,64]},{"name":"101","rect":[64,640,64,64]},{"name":"102","rect":[128,640,64,64]},{"name":"103","rect":[192,640,64,64]},{"name":"104","rect":[256,640,64,64]},{"name":"105","rect":[320,640,64,64]},{"name":"106","rect":[384,640,64,64]},{"name":"107","rect":[448,640,64,64]},{"name":"108","rect":[512,640,64,64]},{"name":"109","rect":[576,640,64,64]},{"name":"110","rect":[0,704,64,64]},{"name":"111","rect":[64,704,64,64]},{"name":"112","rect":[128,704,64,64]},{"name":"113","rect":[192,704,64,64]},{"name":"114","rect":[256,704,64,64]},{"name":"115","rect":[320,704,64,64]},{"name":"116","rect":[384,704,64,64]},{"name":"117","rect":[448,704,64,64]},{"name":"118","rect":[512,704,64,64]},{"name":"119","rect":[576,704,64,64]},{"name":"120","rect":[640,0,64,64]},{"name":"121","rect":[704,0,64,64]},{"name":"122","rect":[768,0,64,64]},{"name":"123","rect":[832,0,64,64]},{"name":"124","rect":[896,0,64,64]},{"name":"125","rect":[640,192,64,64]},{"name":"126","rect":[704,192,64,64]},{"name":"127","rect":[768,192,64,64]},{"name":"128","rect":[832,192,64,64]},{"name":"129","rect":[896,192,64,64]},{"name":"130","rect":[640,64,64,64]},{"name":"131","rect":[704,64,64,64]},{"name":"132","rect":[768,64,64,64]},{"name":"133","rect":[832,64,64,64]},{"name":"134","rect":[896,64,64,64]},{"name":"135","rect":[640,256,64,64]},{"name":"136","rect":[704,256,64,64]},{"name":"137","rect":[768,256,64,64]},{"name":"138","rect":[832,256,64,64]},{"name":"139","rect":[896,256,64,64]},{"name":"140","rect":[640,128,64,64]},{"name":"141","rect":[704,128,64,64]},{"name":"142","rect":[768,128,64,64]},{"name":"143","rect":[832,128,64,64]},{"name":"144","rect":[896,128,64,64]},{"name":"145","rect":[640,320,64,64]},{"name":"146","rect":[704,320,64,64]},{"name":"147","rect":[768,320,64,64]},{"name":"148","rect":[832,320,64,64]},{"name":"149","rect":[896,320,64,64]},{"name":"150","rect":[640,384,64,64]},{"name":"151","rect":[704,384,64,64]},{"name":"152","rect":[768,384,64,64]},{"name":"153","rect":[832,384,64,64]},{"name":"154","rect":[896,384,64,64]},{"name":"155","rect":[640,576,64,64]},{"name":"156","rect":[704,576,64,64]},{"name":"157","rect":[768,576,64,64]},{"name":"158","rect":[832,576,64,64]},{"name":"159","rect":[896,576,64,64]},{"name":"160","rect":[640,448,64,64]},{"name":"161","rect":[704,448,64,64]},{"name":"162","rect":[768,448,64,64]},{"name":"163","rect":[832,448,64,64]},{"name":"164","rect":[896,448,64,64]},{"name":"165","rect":[640,640,64,64]},{"name":"166","rect":[704,640,64,64]},{"name":"167","rect":[768,640,64,64]},{"name":"168","rect":[832,640,64,64]},{"name":"169","rect":[896,640,64,64]},{"name":"170","rect":[640,512,64,64]},{"name":"171","rect":[704,512,64,64]},{"name":"172","rect":[768,512,64,64]},{"name":"173","rect":[832,512,64,64]},{"name":"174","rect":[896,512,64,64]},{"name":"175","rect":[640,704,64,64]},{"name":"176","rect":[704,704,64,64]},{"name":"177","rect":[768,704,64,64]},{"name":"178","rect":[832,704,64,64]},{"name":"179","rect":[896,704,64,64]},{"name":"180","rect":[0,768,64,64]},{"name":"181","rect":[64,768,64,64]},{"name":"182","rect":[128,768,64,64]},{"name":"183","rect":[192,768,64,64]},{"name":"184","rect":[256,768,64,64]},{"name":"185","rect":[320,768,64,64]},{"name":"186","rect":[384,768,64,64]},{"name":"187","rect":[448,768,64,64]},{"name":"188","rect":[512,768,64,64]},{"name":"189","rect":[576,768,64,64]},{"name":"190","rect":[640,768,64,64]},{"name":"191","rect":[704,768,64,64]},{"name":"192","rect":[768,768,64,64]},{"name":"193","rect":[832,768,64,64]},{"name":"194","rect":[896,768,64,64]},{"name":"195","rect":[960,0,64,64]},{"name":"196","rect":[1024,0,64,64]},{"name":"197","rect":[1088,0,64,64]},{"name":"198","rect":[1152,0,64,64]},{"name":"199","rect":[1216,0,64,64]},{"name":"200","rect":[1280,0,64,64]},{"name":"201","rect":[1344,0,64,64]},{"name":"202","rect":[1408,0,64,64]},{"name":"203","rect":[960,64,64,64]},{"name":"204","rect":[1024,64,64,64]},{"name":"205","rect":[1088,64,64,64]},{"name":"206","rect":[1152,64,64,64]},{"name":"207","rect":[1216,64,64,64]},{"name":"208","rect":[1280,64,64,64]},{"name":"209","rect":[1344,64,64,64]},{"name":"210","rect":[1408,64,64,64]},{"name":"211","rect":[960,128,64,64]},{"name":"212","rect":[1024,128,64,64]},{"name":"213","rect":[1088,128,64,64]},{"name":"214","rect":[1152,128,64,64]},{"name":"215","rect":[1216,128,64,64]},{"name":"216","rect":[1280,128,64,64]},{"name":"217","rect":[1344,128,64,64]},{"name":"218","rect":[1408,128,64,64]},{"name":"219","rect":[960,192,64,64]},{"name":"220","rect":[1024,192,64,64]},{"name":"221","rect":[1088,192,64,64]},{"name":"222","rect":[1152,192,64,64]},{"name":"223","rect":[1216,192,64,64]},{"name":"224","rect":[1280,192,64,64]},{"name":"225","rect":[1344,192,64,64]},{"name":"226","rect":[1408,192,64,64]},{"name":"227","rect":[960,256,64,64]},{"name":"228","rect":[1024,256,64,64]},{"name":"229","rect":[1088,256,64,64]},{"name":"230","rect":[1152,256,64,64]},{"name":"231","rect":[1216,256,64,64]},{"name":"232","rect":[1280,256,64,64]},{"name":"233","rect":[1344,256,64,64]},{"name":"234","rect":[1408,256,64,64]},{"name":"235","rect":[960,320,64,64]},{"name":"236","rect":[1024,320,64,64]},{"name":"237","rect":[1088,320,64,64]},{"name":"238","rect":[1152,320,64,64]},{"name":"239","rect":[1216,320,64,64]},{"name":"240","rect":[1280,320,64,64]},{"name":"241","rect":[1344,320,64,64]},{"name":"242","rect":[1408,320,64,64]},{"name":"243","rect":[960,384,64,64]},{"name":"244","rect":[1024,384,64,64]},{"name":"245","rect":[1088,384,64,64]},{"name":"246","rect":[1152,384,64,64]},{"name":"247","rect":[1216,384,64,64]},{"name":"248","rect":[1280,384,64,64]},{"name":"249","rect":[1344,384,64,64]},{"name":"250","rect":[1408,384,64,64]},{"name":"251","rect":[960,448,64,64]},{"name":"252","rect":[1024,448,64,64]},{"name":"253","rect":[1088,448,64,64]},{"name":"254","rect":[1152,448,64,64]},{"name":"255","rect":[1216,448,64,64]},{"name":"256","rect":[1280,448,64,64]},{"name":"257","rect":[1344,448,64,64]},{"name":"258","rect":[1408,448,64,64]},{"name":"259","rect":[960,512,64,64]},{"name":"260","rect":[1024,512,64,64]},{"name":"261","rect":[1088,512,64,64]},{"name":"262","rect":[1152,512,64,64]},{"name":"263","rect":[1216,512,64,64]},{"name":"264","rect":[1280,512,64,64]},{"name":"265","rect":[1344,512,64,64]},{"name":"266","rect":[1408,512,64,64]},{"name":"267","rect":[960,576,64,64]},{"name":"268","rect":[1024,576,64,64]},{"name":"269","rect":[1088,576,64,64]},{"name":"270","rect":[1152,576,64,64]},{"name":"271","rect":[1216,576,64,64]},{"name":"272","rect":[1280,576,64,64]},{"name":"273","rect":[1344,576,64,64]},{"name":"274","rect":[1408,576,64,64]},{"name":"275","rect":[960,640,64,64]},{"name":"276","rect":[1024,640,64,64]},{"name":"277","rect":[1088,640,64,64]},{"name":"278","rect":[1152,640,64,64]},{"name":"279","rect":[1216,640,64,64]},{"name":"280","rect":[1280,640,64,64]},{"name":"281","rect":[1344,640,64,64]},{"name":"282","rect":[1408,640,64,64]},{"name":"283","rect":[960,704,64,64]},{"name":"284","rect":[1024,704,64,64]},{"name":"285","rect":[1088,704,64,64]},{"name":"286","rect":[1152,704,64,64]},{"name":"287","rect":[1216,704,64,64]},{"name":"288","rect":[1280,704,64,64]},{"name":"289","rect":[1344,704,64,64]},{"name":"290","rect":[1408,704,64,64]},{"name":"291","rect":[960,768,64,64]},{"name":"292","rect":[1024,768,64,64]},{"name":"293","rect":[1088,768,64,64]},{"name":"294","rect":[1152,768,64,64]},{"name":"295","rect":[1216,768,64,64]},{"name":"296","rect":[1280,768,64,64]},{"name":"297","rect":[1344,768,64,64]},{"name":"298","rect":[1408,768,64,64]}],"groups":[]}
